ding/__init__.py
ding/__main__.py
ding/after.py
onhold_ding-0.1.0.dist-info/LICENSE
onhold_ding-0.1.0.dist-info/METADATA
onhold_ding-0.1.0.dist-info/WHEEL
onhold_ding-0.1.0.dist-info/entry_points.txt
onhold_ding-0.1.0.dist-info/top_level.txt
onhold_ding-0.1.0.dist-info/RECORD
