Metadata-Version: 2.1
Name: onhold-ding
Version: 0.1.0
Summary: 🔊 Play music after jobs complete
Home-page: https://alexdelorenzo.dev
Author: Alex DeLorenzo
License: AGPL-3.0
Platform: UNKNOWN
Requires-Python: >=3.6
Requires-Dist: click (==7.1.2)
Requires-Dist: onhold (>=0.3.8)
Requires-Dist: play-sounds (==0.1.1)
